LICENSE.txt
MANIFEST.in
README.txt
setup.py
whisker_serial_order/__init__.py
whisker_serial_order/alembic.ini
whisker_serial_order/constants.py
whisker_serial_order/extra.py
whisker_serial_order/gui.py
whisker_serial_order/main.py
whisker_serial_order/models.py
whisker_serial_order/settings.py
whisker_serial_order/task.py
whisker_serial_order/version.py
whisker_serial_order.egg-info/PKG-INFO
whisker_serial_order.egg-info/SOURCES.txt
whisker_serial_order.egg-info/dependency_links.txt
whisker_serial_order.egg-info/entry_points.txt
whisker_serial_order.egg-info/requires.txt
whisker_serial_order.egg-info/top_level.txt
whisker_serial_order/alembic/env.py
whisker_serial_order/alembic/script.py.mako
whisker_serial_order/alembic/versions/0001_start.py
whisker_serial_order/alembic/versions/0002_sessionlimit.py
whisker_serial_order/alembic/versions/0003_filename.py
whisker_serial_order/alembic/versions/0004_software_version.py
whisker_serial_order/alembic/versions/__pycache__